odoo/addons/product_state_sale/README.rst
odoo/addons/product_state_sale/__init__.py
odoo/addons/product_state_sale/__manifest__.py
odoo/addons/product_state_sale/i18n/it.po
odoo/addons/product_state_sale/i18n/nl.po
odoo/addons/product_state_sale/i18n/product_state_sale.pot
odoo/addons/product_state_sale/readme/CONTRIBUTORS.md
odoo/addons/product_state_sale/readme/CREDITS.md
odoo/addons/product_state_sale/readme/DESCRIPTION.md
odoo/addons/product_state_sale/readme/USAGE.md
odoo/addons/product_state_sale/security/security.xml
odoo/addons/product_state_sale/static/description/icon.png
odoo/addons/product_state_sale/static/description/index.html
odoo/addons/product_state_sale/views/product_state_views.xml
odoo_addon_product_state_sale-18.0.1.0.0.6.dist-info/METADATA
odoo_addon_product_state_sale-18.0.1.0.0.6.dist-info/WHEEL
odoo_addon_product_state_sale-18.0.1.0.0.6.dist-info/top_level.txt
odoo_addon_product_state_sale-18.0.1.0.0.6.dist-info/RECORD
